odoo/addons/sale_blanket_order_template/LICENSE
odoo/addons/sale_blanket_order_template/README.rst
odoo/addons/sale_blanket_order_template/__init__.py
odoo/addons/sale_blanket_order_template/__manifest__.py
odoo/addons/sale_blanket_order_template/i18n/de.po
odoo/addons/sale_blanket_order_template/images/screen.png
odoo/addons/sale_blanket_order_template/models/__init__.py
odoo/addons/sale_blanket_order_template/models/blanket_order.py
odoo/addons/sale_blanket_order_template/static/description/icon.png
odoo/addons/sale_blanket_order_template/static/description/index.html
odoo/addons/sale_blanket_order_template/tests/TEST_INSTRUCTIONS.rst
odoo/addons/sale_blanket_order_template/views/sale_blanket_order.xml
odoo_addon_sale_blanket_order_template-16.0.1.0.0.dist-info/METADATA
odoo_addon_sale_blanket_order_template-16.0.1.0.0.dist-info/WHEEL
odoo_addon_sale_blanket_order_template-16.0.1.0.0.dist-info/top_level.txt
odoo_addon_sale_blanket_order_template-16.0.1.0.0.dist-info/RECORD
